LICENSE
README.md
setup.py
CodeChroma/__init__.py
CodeChroma/colors.py
CodeChroma/terminalColors.py
CodeChroma.egg-info/PKG-INFO
CodeChroma.egg-info/SOURCES.txt
CodeChroma.egg-info/dependency_links.txt
CodeChroma.egg-info/requires.txt
CodeChroma.egg-info/top_level.txt