Metadata-Version: 2.1
Name: CodeChroma
Version: 1.5.0
Summary: This project is a simple library to color text in the terminal with python.
Home-page: https://github.com/EddyBel/CodeChroma
Download-URL: https://github.com/EddyBel/CodeChroma
Author: Eduardo Rangel
Author-email: dante61918@gmail.com
License: MIT
Keywords: colors,syntax,terminal,markdown
Requires-Python: >=3.7
License-File: LICENSE
